fad/__init__.py
fad/__main__.py
fad/constants.py
fad/scraper.py
fad/utils.py
fad-0.0.4.dist-info/LICENSE
fad-0.0.4.dist-info/METADATA
fad-0.0.4.dist-info/WHEEL
fad-0.0.4.dist-info/entry_points.txt
fad-0.0.4.dist-info/top_level.txt
fad-0.0.4.dist-info/RECORD
