Metadata-Version: 2.1
Name: fad
Version: 0.0.4
Summary: Download an album of photos from facebook
Home-page: https://github.com/wuallanx/facebook-album-downloader
Author: Allan Wu
Author-email: wuallanx@gmail.com
License: GNU GPLv3
Project-URL: Bug Tracker, https://github.com/wuallanx/facebook-album-downloader/issues
Platform: UNKNOWN
Classifier: License :: OSI Approved :: GNU General Public License v3 (GPLv3)
Classifier: Operating System :: OS Independent
Classifier: Programming Language :: Python :: 3
Classifier: Programming Language :: Python :: 3.9
Requires-Python: >=3.9
License-File: LICENSE
Requires-Dist: requests (==2.26.0)
Requires-Dist: selenium (==4.0.0)
